pptesting/__init__.py
pptesting/main.py
pptesting-0.3.0.dist-info/METADATA
pptesting-0.3.0.dist-info/WHEEL
pptesting-0.3.0.dist-info/entry_points.txt
pptesting-0.3.0.dist-info/top_level.txt
pptesting-0.3.0.dist-info/RECORD
