Metadata-Version: 2.1
Name: pptesting
Version: 0.3.0
Requires-Dist: numpy
Requires-Dist: pandas
